{"title": "Docker", "uid": "a48e6dda0c21e40880cba7e763278b04", "slug": "docker", "date": "2023-05-13 06:43:14", "updated": "2023-05-16 15:10:00.175000", "comments": true, "path": "api/articles/docker.json", "keywords": null, "cover": "/img/docker/docker.webp", "content": "<p>Docker的应用与实践</p>\n<h2 id=\"docker镜像制作\"><a href=\"#docker镜像制作\" class=\"headerlink\" title=\"docker镜像制作\"></a>docker镜像制作</h2><h2 id=\"Dockerfile编写规则\"><a href=\"#Dockerfile编写规则\" class=\"headerlink\" title=\"Dockerfile编写规则\"></a>Dockerfile编写规则</h2><h2 id=\"docker-compose容器编排\"><a href=\"#docker-compose容器编排\" class=\"headerlink\" title=\"docker-compose容器编排\"></a>docker-compose容器编排</h2>", "feature": false, "text": "Docker的应用与实践 docker镜像制作Dockerfile编写规则docker-compose容器编排", "link": "", "photos": [], "count_time": {"symbolsCount": 55, "symbolsTime": "1 mins."}, "categories": [{"name": "测试", "slug": "测试", "count": 4, "path": "api/categories/测试.json"}], "tags": [{"name": "docker", "slug": "docker", "count": 1, "path": "api/tags/docker.json"}], "toc": "<ol class=\"toc\"><li class=\"toc-item toc-level-2\"><a class=\"toc-link\" href=\"#docker%E9%95%9C%E5%83%8F%E5%88%B6%E4%BD%9C\"><span class=\"toc-text\">docker镜像制作</span></a></li><li class=\"toc-item toc-level-2\"><a class=\"toc-link\" href=\"#Dockerfile%E7%BC%96%E5%86%99%E8%A7%84%E5%88%99\"><span class=\"toc-text\">Dockerfile编写规则</span></a></li><li class=\"toc-item toc-level-2\"><a class=\"toc-link\" href=\"#docker-compose%E5%AE%B9%E5%99%A8%E7%BC%96%E6%8E%92\"><span class=\"toc-text\">docker-compose容器编排</span></a></li></ol>", "author": {"name": "倪传方", "slug": "blog-author", "avatar": "/img/site/avatar.webp", "link": "/", "description": "一位正在重塑知识的技术人 <br /> @ <b>微信：ncf08209270</b>", "socials": {"github": "https://github.com/nichuanfang", "twitter": "https://twitter.com/jayzhouzj", "stackoverflow": "https://stackoverflow.com/users/12083298/jaychou", "wechat": "", "qq": "", "weibo": "", "zhihu": "https://www.zhihu.com/people/ba-dao-yi-shan-zhu", "csdn": "https://blog.csdn.net/Saphroth", "juejin": "https://juejin.cn/user/2740456686366830", "customs": {}}}, "mapped": true, "prev_post": {}, "next_post": {"title": "order", "uid": "96f09adce96be674e5e8c51b917f51c6", "slug": "order", "date": "2023-05-12 07:14:59", "updated": "2023-05-16 15:10:00.175000", "comments": true, "path": "api/articles/order.json", "keywords": null, "cover": "/img/order/order.webp", "content": "<h2 id=\"测试文章的推荐顺序\"><a href=\"#测试文章的推荐顺序\" class=\"headerlink\" title=\"测试文章的推荐顺序\"></a>测试文章的推荐顺序</h2>", "feature": false, "text": "测试文章的推荐顺序", "link": "", "photos": [], "count_time": {"symbolsCount": 9, "symbolsTime": "1 mins."}, "categories": [{"name": "测试", "slug": "测试", "count": 4, "path": "api/categories/测试.json"}], "tags": [{"name": "test", "slug": "test", "count": 1, "path": "api/tags/test.json"}], "toc": "<ol class=\"toc\"><li class=\"toc-item toc-level-2\"><a class=\"toc-link\" href=\"#%E6%B5%8B%E8%AF%95%E6%96%87%E7%AB%A0%E7%9A%84%E6%8E%A8%E8%8D%90%E9%A1%BA%E5%BA%8F\"><span class=\"toc-text\">测试文章的推荐顺序</span></a></li></ol>", "author": {"name": "倪传方", "slug": "blog-author", "avatar": "/img/site/avatar.webp", "link": "/", "description": "一位正在重塑知识的技术人 <br /> @ <b>微信：ncf08209270</b>", "socials": {"github": "https://github.com/nichuanfang", "twitter": "https://twitter.com/jayzhouzj", "stackoverflow": "https://stackoverflow.com/users/12083298/jaychou", "wechat": "", "qq": "", "weibo": "", "zhihu": "https://www.zhihu.com/people/ba-dao-yi-shan-zhu", "csdn": "https://blog.csdn.net/Saphroth", "juejin": "https://juejin.cn/user/2740456686366830", "customs": {}}}, "mapped": true}}